test_tunnel/__init__.py
test_tunnel/addresses.py
test_tunnel/defs.py
test_tunnel/py.typed
test_tunnel/run_test.py
test_tunnel/cmd_test/__init__.py
test_tunnel/cmd_test/microsocks.py
test_tunnel/cmd_test/socat.py
test_tunnel/cmd_test/util.py
test_tunnel-0.1.1.dist-info/METADATA
test_tunnel-0.1.1.dist-info/WHEEL
test_tunnel-0.1.1.dist-info/RECORD
